src/encoder8x3.v
module encoder8x3(input wire [7:0] i, output reg [2:0] a);
// One-hot only. Zero and multi-hot inputs return 000 (not a priority encoder).
always @* begin
case (i)
8'h80: a = 0; 8'h40: a = 1; 8'h20: a = 2; 8'h10: a = 3;
8'h08: a = 4; 8'h04: a = 5; 8'h02: a = 6; 8'h01: a = 7;
default: a = 0;
endcase
end
endmodule

sim/tb_encoder8x3.sv
`timescale 1ns/1ps
module tb_encoder8x3;
reg [7:0] i; wire [2:0] a; integer k; encoder8x3 dut(i,a);
integer n, checked = 0;
reg [2:0] expected;
initial begin
$dumpfile("wave.vcd"); $dumpvars(0,tb_encoder8x3);

for(n=0;n<256;n=n+1) begin
i=n;
expected=0;
for(k=0;k<8;k=k+1) if(n==(128>>k)) expected=k;
#10;
if (a !== expected)
$fatal(1, "FAIL encoder8x3 vector=%0d expected=%h actual=%h", n, expected, a);
checked=checked+1;
end
if (checked!=256) $fatal(1, "Incomplete test");
$display("LAB1_PASS encoder8x3 cases=%0d", checked);
$finish;
end
initial begin #100000; $fatal(1, "Watchdog"); end
endmodule

encoder8x3.sim/sim_1/behav/xsim/wave.vcd
$date
   Mon Sep 14 17:58:13 2026
$end

$version
  2026.1
  $dumpfile ("wave.vcd") 
$end

$timescale
  1ps
$end

$scope module tb_encoder8x3 $end
$var reg 8 ! i [7:0] $end
$var wire 3 " a [2:0] $end
$var integer 32 # k [31:0] $end
$var integer 32 $ n [31:0] $end
$var integer 32 % checked [31:0] $end
$var reg 3 & expected [2:0] $end
$scope module dut $end
$var wire 8 ' i [7:0] $end
$var reg 3 ( a [2:0] $end
$upscope $end
$upscope $end
$enddefinitions $end

#0
$dumpvars
b0 !
b0 "
b1000 #
b0 $
b0 %
b0 &
b0 '
b0 (
$end

#10000
b1 !
b111 "
b1000 #
b1 $
b1 %
b111 &
b1 '
b111 (

#20000
b10 !
b110 "
b1000 #
b10 $
b10 %
b110 &
b10 '
b110 (

#30000
b11 !
b0 "
b1000 #
b11 $
b11 %
b0 &
b11 '
b0 (

#40000
b100 !
b101 "
b1000 #
b100 $
b100 %
b101 &
b100 '
b101 (

#50000
b101 !
b0 "
b1000 #
b101 $
b101 %
b0 &
b101 '
b0 (

#60000
b110 !
b1000 #
b110 $
b110 %
b110 '

#70000
b111 !
b1000 #
b111 $
b111 %
b111 '

#80000
b1000 !
b100 "
b1000 #
b1000 $
b1000 %
b100 &
b1000 '
b100 (

#90000
b1001 !
b0 "
b1000 #
b1001 $
b1001 %
b0 &
b1001 '
b0 (

#100000
b1010 !
b1000 #
b1010 $
b1010 %
b1010 '

#110000
b1011 !
b1000 #
b1011 $
b1011 %
b1011 '

#120000
b1100 !
b1000 #
b1100 $
b1100 %
b1100 '

#130000
b1101 !
b1000 #
b1101 $
b1101 %
b1101 '

#140000
b1110 !
b1000 #
b1110 $
b1110 %
b1110 '

#150000
b1111 !
b1000 #
b1111 $
b1111 %
b1111 '

#160000
b10000 !
b11 "
b1000 #
b10000 $
b10000 %
b11 &
b10000 '
b11 (

#170000
b10001 !
b0 "
b1000 #
b10001 $
b10001 %
b0 &
b10001 '
b0 (

#180000
b10010 !
b1000 #
b10010 $
b10010 %
b10010 '

#190000
b10011 !
b1000 #
b10011 $
b10011 %
b10011 '

#200000
b10100 !
b1000 #
b10100 $
b10100 %
b10100 '

#210000
b10101 !
b1000 #
b10101 $
b10101 %
b10101 '

#220000
b10110 !
b1000 #
b10110 $
b10110 %
b10110 '

#230000
b10111 !
b1000 #
b10111 $
b10111 %
b10111 '

#240000
b11000 !
b1000 #
b11000 $
b11000 %
b11000 '

#250000
b11001 !
b1000 #
b11001 $
b11001 %
b11001 '

#260000
b11010 !
b1000 #
b11010 $
b11010 %
b11010 '

#270000
b11011 !
b1000 #
b11011 $
b11011 %
b11011 '

#280000
b11100 !
b1000 #
b11100 $
b11100 %
b11100 '

#290000
b11101 !
b1000 #
b11101 $
b11101 %
b11101 '

#300000
b11110 !
b1000 #
b11110 $
b11110 %
b11110 '

#310000
b11111 !
b1000 #
b11111 $
b11111 %
b11111 '

#320000
b100000 !
b10 "
b1000 #
b100000 $
b100000 %
b10 &
b100000 '
b10 (

#330000
b100001 !
b0 "
b1000 #
b100001 $
b100001 %
b0 &
b100001 '
b0 (

#340000
b100010 !
b1000 #
b100010 $
b100010 %
b100010 '

#350000
b100011 !
b1000 #
b100011 $
b100011 %
b100011 '

#360000
b100100 !
b1000 #
b100100 $
b100100 %
b100100 '

#370000
b100101 !
b1000 #
b100101 $
b100101 %
b100101 '

#380000
b100110 !
b1000 #
b100110 $
b100110 %
b100110 '

#390000
b100111 !
b1000 #
b100111 $
b100111 %
b100111 '

#400000
b101000 !
b1000 #
b101000 $
b101000 %
b101000 '

#410000
b101001 !
b1000 #
b101001 $
b101001 %
b101001 '

#420000
b101010 !
b1000 #
b101010 $
b101010 %
b101010 '

#430000
b101011 !
b1000 #
b101011 $
b101011 %
b101011 '

#440000
b101100 !
b1000 #
b101100 $
b101100 %
b101100 '

#450000
b101101 !
b1000 #
b101101 $
b101101 %
b101101 '

#460000
b101110 !
b1000 #
b101110 $
b101110 %
b101110 '

#470000
b101111 !
b1000 #
b101111 $
b101111 %
b101111 '

#480000
b110000 !
b1000 #
b110000 $
b110000 %
b110000 '

#490000
b110001 !
b1000 #
b110001 $
b110001 %
b110001 '

#500000
b110010 !
b1000 #
b110010 $
b110010 %
b110010 '

#510000
b110011 !
b1000 #
b110011 $
b110011 %
b110011 '

#520000
b110100 !
b1000 #
b110100 $
b110100 %
b110100 '

#530000
b110101 !
b1000 #
b110101 $
b110101 %
b110101 '

#540000
b110110 !
b1000 #
b110110 $
b110110 %
b110110 '

#550000
b110111 !
b1000 #
b110111 $
b110111 %
b110111 '

#560000
b111000 !
b1000 #
b111000 $
b111000 %
b111000 '

#570000
b111001 !
b1000 #
b111001 $
b111001 %
b111001 '

#580000
b111010 !
b1000 #
b111010 $
b111010 %
b111010 '

#590000
b111011 !
b1000 #
b111011 $
b111011 %
b111011 '

#600000
b111100 !
b1000 #
b111100 $
b111100 %
b111100 '

#610000
b111101 !
b1000 #
b111101 $
b111101 %
b111101 '

#620000
b111110 !
b1000 #
b111110 $
b111110 %
b111110 '

#630000
b111111 !
b1000 #
b111111 $
b111111 %
b111111 '

#640000
b1000000 !
b1 "
b1000 #
b1000000 $
b1000000 %
b1 &
b1000000 '
b1 (

#650000
b1000001 !
b0 "
b1000 #
b1000001 $
b1000001 %
b0 &
b1000001 '
b0 (

#660000
b1000010 !
b1000 #
b1000010 $
b1000010 %
b1000010 '

#670000
b1000011 !
b1000 #
b1000011 $
b1000011 %
b1000011 '

#680000
b1000100 !
b1000 #
b1000100 $
b1000100 %
b1000100 '

#690000
b1000101 !
b1000 #
b1000101 $
b1000101 %
b1000101 '

#700000
b1000110 !
b1000 #
b1000110 $
b1000110 %
b1000110 '

#710000
b1000111 !
b1000 #
b1000111 $
b1000111 %
b1000111 '

#720000
b1001000 !
b1000 #
b1001000 $
b1001000 %
b1001000 '

#730000
b1001001 !
b1000 #
b1001001 $
b1001001 %
b1001001 '

#740000
b1001010 !
b1000 #
b1001010 $
b1001010 %
b1001010 '

#750000
b1001011 !
b1000 #
b1001011 $
b1001011 %
b1001011 '

#760000
b1001100 !
b1000 #
b1001100 $
b1001100 %
b1001100 '

#770000
b1001101 !
b1000 #
b1001101 $
b1001101 %
b1001101 '

#780000
b1001110 !
b1000 #
b1001110 $
b1001110 %
b1001110 '

#790000
b1001111 !
b1000 #
b1001111 $
b1001111 %
b1001111 '

#800000
b1010000 !
b1000 #
b1010000 $
b1010000 %
b1010000 '

#810000
b1010001 !
b1000 #
b1010001 $
b1010001 %
b1010001 '

#820000
b1010010 !
b1000 #
b1010010 $
b1010010 %
b1010010 '

#830000
b1010011 !
b1000 #
b1010011 $
b1010011 %
b1010011 '

#840000
b1010100 !
b1000 #
b1010100 $
b1010100 %
b1010100 '

#850000
b1010101 !
b1000 #
b1010101 $
b1010101 %
b1010101 '

#860000
b1010110 !
b1000 #
b1010110 $
b1010110 %
b1010110 '

#870000
b1010111 !
b1000 #
b1010111 $
b1010111 %
b1010111 '

#880000
b1011000 !
b1000 #
b1011000 $
b1011000 %
b1011000 '

#890000
b1011001 !
b1000 #
b1011001 $
b1011001 %
b1011001 '

#900000
b1011010 !
b1000 #
b1011010 $
b1011010 %
b1011010 '

#910000
b1011011 !
b1000 #
b1011011 $
b1011011 %
b1011011 '

#920000
b1011100 !
b1000 #
b1011100 $
b1011100 %
b1011100 '

#930000
b1011101 !
b1000 #
b1011101 $
b1011101 %
b1011101 '

#940000
b1011110 !
b1000 #
b1011110 $
b1011110 %
b1011110 '

#950000
b1011111 !
b1000 #
b1011111 $
b1011111 %
b1011111 '

#960000
b1100000 !
b1000 #
b1100000 $
b1100000 %
b1100000 '

#970000
b1100001 !
b1000 #
b1100001 $
b1100001 %
b1100001 '

#980000
b1100010 !
b1000 #
b1100010 $
b1100010 %
b1100010 '

#990000
b1100011 !
b1000 #
b1100011 $
b1100011 %
b1100011 '

#1000000
b1100100 !
b1000 #
b1100100 $
b1100100 %
b1100100 '
